{
    "data": [
        {
            "title": "手机电脑",
            "picture": "https://gfs11.gomein.net.cn/wireless/T1BZd_BgD_1RCvBVdK_195_129.png"
        },
        {
            "title": "国美电器",
            "picture": "https://gfs13.gomein.net.cn/wireless/T11gZvBChQ1RCvBVdK_195_129.png"
        },
        {
            "title": "国美超市",
            "picture": "https://gfs12.gomein.net.cn/wireless/T1uZDsByhv1RCvBVdK_195_129.png"
        },
        {
            "title": "美店组团",
            "picture": "https://gfs10.gomein.net.cn/wireless/T1k3D_B_L_1RCvBVdK_195_129.png"
        },
        {
            "title": "分期购",
            "picture": "https://gfs13.gomein.net.cn/wireless/T1p0dsBsbv1RCvBVdK_195_129.png"
        },
        {
            "title": "充值服务",
            "picture": "https://gfs11.gomein.net.cn/wireless/T1Ii_bBmbb1RCvBVdK_195_129.png"
        },
        {
            "title": "国美家装",
            "picture": "https://gfs11.gomein.net.cn/wireless/T1u.K_B5W_1RCvBVdK_195_129.png"
        },
        {
            "title": "领美豆",
            "picture": "https://gfs13.gomein.net.cn/wireless/T1vGdsBsLv1RCvBVdK_195_129.png"
        },
        {
            "title": "国美管家",
            "picture": "https://gfs11.gomein.net.cn/wireless/T1J9_vBgxb1RCvBVdK_195_129.png"
        },
        {
            "title": "我的",
            "picture": "https://gfs10.gomein.net.cn/wireless/T11MWbBQhv1RCvBVdK_195_129.png"
        }
    ]
}